agent_primitives/__init__.py
agent_primitives/failures.py
agent_primitives/py.typed
agent_primitives-0.2.0.dist-info/METADATA
agent_primitives-0.2.0.dist-info/WHEEL
agent_primitives-0.2.0.dist-info/top_level.txt
agent_primitives-0.2.0.dist-info/RECORD
