Metadata-Version: 2.4
Name: agent-primitives
Version: 0.2.0
Summary: Shared primitive data models for Agent OS - failure types, severity levels, and base structures
Author-email: Imran Siddique <imran@example.com>
License: MIT
Project-URL: Homepage, https://github.com/imran-siddique/agent-primitives
Project-URL: Repository, https://github.com/imran-siddique/agent-primitives.git
Project-URL: Issues, https://github.com/imran-siddique/agent-primitives/issues
Keywords: agent,ai,llm,primitives,models,failures,multi-agent
Classifier: Development Status :: 4 - Beta
Classifier: Intended Audience :: Developers
Classifier: License :: OSI Approved :: MIT License
Classifier: Programming Language :: Python :: 3
Classifier: Programming Language :: Python :: 3.8
Classifier: Programming Language :: Python :: 3.9
Classifier: Programming Language :: Python :: 3.10
Classifier: Programming Language :: Python :: 3.11
Classifier: Programming Language :: Python :: 3.12
Classifier: Operating System :: OS Independent
Classifier: Typing :: Typed
Requires-Python: >=3.8
Requires-Dist: pydantic>=2.0.0
Provides-Extra: dev
Requires-Dist: pytest>=7.4.0; extra == "dev"
Requires-Dist: mypy>=1.8.0; extra == "dev"
Requires-Dist: ruff>=0.1.0; extra == "dev"
